canned_views/__init__.py
canned_views/admin.py
canned_views/admin_site.py
canned_views/apps.py
canned_views/auth_objects.py
canned_views/auths.py
canned_views/constants.py
canned_views/forms.py
canned_views/models.py
canned_views/urls.py
canned_views/utils.py
canned_views/migrations/0001_initial.py
canned_views/migrations/0002_cannedviews_columns_cannedviews_order_by_and_more.py
canned_views/migrations/0003_remove_cannedviews_columns_and_more.py
canned_views/migrations/0004_auto_20220617_2306.py
canned_views/migrations/0005_auto_20220617_2344.py
canned_views/migrations/0006_cannedviews_filter_by_current_site_and_more.py
canned_views/migrations/0007_cannedviews_linked_column_name_and_more.py
canned_views/migrations/0008_rename_cannedviews_cannedview_and_more.py
canned_views/migrations/0009_auto_20220704_1841.py
canned_views/migrations/0010_alter_cannedview_managers.py
canned_views/migrations/0011_alter_cannedview_options.py
canned_views/migrations/__init__.py
canned_views/templates/canned_views/base.html
canned_views/templates/canned_views/base_dj3.html
canned_views/templates/canned_views/button.html
canned_views/templates/canned_views/canned_view.html
canned_views/templates/canned_views/home.html
canned_views/templatetags/__init__.py
canned_views/templatetags/canned_extras.py
canned_views/tests/__init__.py
canned_views/tests/tests/__init__.py
canned_views/views/__init__.py
canned_views/views/basic_view.py
canned_views/views/home_view.py
canned_views_app/__init__.py
canned_views_app/apps.py
canned_views_app/asgi.py
canned_views_app/manage.py
canned_views_app/navbars.py
canned_views_app/settings.py
canned_views_app/urls.py
canned_views_app/views.py
canned_views_app/wsgi.py
canned_views_app/templates/canned_views_app/base.html
canned_views_app/templates/canned_views_app/home.html
canned_views-0.1.8.dist-info/AUTHORS
canned_views-0.1.8.dist-info/LICENSE
canned_views-0.1.8.dist-info/METADATA
canned_views-0.1.8.dist-info/WHEEL
canned_views-0.1.8.dist-info/top_level.txt
canned_views-0.1.8.dist-info/RECORD
