Metadata-Version: 2.1
Name: canned-views
Version: 0.1.8
Summary: SQL views presented as simple Django ListView reports
Home-page: https://github.com/erikvw/canned-views
Author: Erik van Widenfelt
Author-email: ew2789@gmail.com
License: GPL license, see LICENSE
Keywords: django sql view ListView,clinicedc,clinical trials
Classifier: Environment :: Web Environment
Classifier: Framework :: Django
Classifier: Framework :: Django :: 4.1
Classifier: Intended Audience :: Developers
Classifier: Intended Audience :: Science/Research
Classifier: Operating System :: OS Independent
Classifier: Programming Language :: Python :: 3.11
Classifier: License :: OSI Approved :: GNU General Public License v3 (GPLv3)
Requires-Python: >=3.11
License-File: LICENSE
License-File: AUTHORS
Requires-Dist: sqlvalidator
